{
  "timestamp": "2025-12-04 15:26:04",
  "symbols": {
    "RELIANCE": {
      "strikes": {
        "1480": {
          "ema_ltp": 6.15,
          "cum_vwap_num": 9981.45,
          "cum_vol": 1623,
          "iv": 16.85,
          "coi": -62
        },
        "1490": {
          "ema_ltp": 7.10625,
          "cum_vwap_num": 34464.4,
          "cum_vol": 5141,
          "iv": 16.75,
          "coi": 34
        },
        "1500": {
          "ema_ltp": 9.10625,
          "cum_vwap_num": 243327.39999999997,
          "cum_vol": 29668,
          "iv": 16.69,
          "coi": -75
        },
        "1510": {
          "ema_ltp": 11.532174706924707,
          "cum_vwap_num": 419105.69999999995,
          "cum_vol": 42196,
          "iv": 16.55,
          "coi": 7
        },
        "1520": {
          "ema_ltp": 14.543401364283488,
          "cum_vwap_num": 1076816.5,
          "cum_vol": 90179,
          "iv": 16.59,
          "coi": -17
        },
        "1530": {
          "ema_ltp": 18.14291077888016,
          "cum_vwap_num": 2728347.900000001,
          "cum_vol": 212926,
          "iv": 16.63,
          "coi": 151
        },
        "1540": {
          "ema_ltp": 22.491452376899097,
          "cum_vwap_num": 5705090.850000001,
          "cum_vol": 354627,
          "iv": 16.72,
          "coi": 220
        },
        "1550": {
          "ema_ltp": 27.253408217724292,
          "cum_vwap_num": 8788426.599999998,
          "cum_vol": 468022,
          "iv": 16.75,
          "coi": 245
        },
        "1560": {
          "ema_ltp": 33.04031948144626,
          "cum_vwap_num": 11878065.099999998,
          "cum_vol": 544182,
          "iv": 16.97,
          "coi": 125
        },
        "1570": {
          "ema_ltp": 39.04371161355577,
          "cum_vwap_num": 11574123.800000004,
          "cum_vol": 466420,
          "iv": 17.16,
          "coi": -67
        },
        "1580": {
          "ema_ltp": 45.82995608864174,
          "cum_vwap_num": 11091352.05,
          "cum_vol": 377384,
          "iv": 17.62,
          "coi": -94
        }
      },
      "meta": {
        "underlying": 1534.2
      }
    },
    "INFY": {
      "strikes": {
        "1500": {
          "ema_ltp": 4.456916224956513,
          "cum_vwap_num": 595485.5499999999,
          "cum_vol": 92614,
          "iv": 21.23,
          "coi": 365
        },
        "1520": {
          "ema_ltp": 6.539923423528672,
          "cum_vwap_num": 513487.7,
          "cum_vol": 57019,
          "iv": 20.51,
          "coi": 5
        },
        "1540": {
          "ema_ltp": 9.617900311946869,
          "cum_vwap_num": 1142652.05,
          "cum_vol": 83103,
          "iv": 20.09,
          "coi": 254
        },
        "1560": {
          "ema_ltp": 14.015908187627792,
          "cum_vwap_num": 2607382.45,
          "cum_vol": 131634,
          "iv": 19.52,
          "coi": 697
        },
        "1580": {
          "ema_ltp": 20.145178055763246,
          "cum_vwap_num": 2762480.25,
          "cum_vol": 107278,
          "iv": 19.24,
          "coi": 596
        },
        "1600": {
          "ema_ltp": 28.038786000013353,
          "cum_vwap_num": 3746431.2,
          "cum_vol": 111039,
          "iv": 18.95,
          "coi": 1663
        },
        "1620": {
          "ema_ltp": 38.58050845861435,
          "cum_vwap_num": 764951.45,
          "cum_vol": 17983,
          "iv": 19.1,
          "coi": 454
        },
        "1640": {
          "ema_ltp": 52.04157791733742,
          "cum_vwap_num": 590827.0499999999,
          "cum_vol": 10179,
          "iv": 19.82,
          "coi": -20
        },
        "1660": {
          "ema_ltp": 67.22376819849015,
          "cum_vwap_num": 70197.1,
          "cum_vol": 953,
          "iv": 20.89,
          "coi": 8
        },
        "1680": {
          "ema_ltp": 83.57303471565247,
          "cum_vwap_num": 29752.999999999993,
          "cum_vol": 319,
          "iv": 22.18,
          "coi": -2
        },
        "1700": {
          "ema_ltp": 101.31796875,
          "cum_vwap_num": 23935.5,
          "cum_vol": 233,
          "iv": 24.5,
          "coi": -8
        }
      },
      "meta": {
        "underlying": 1596.7
      }
    },
    "HDFCBANK": {
      "strikes": {
        "975": {
          "ema_ltp": 5.790625,
          "cum_vwap_num": 15099.6,
          "cum_vol": 2574,
          "iv": 15.89,
          "coi": 23
        },
        "980": {
          "ema_ltp": 6.865625,
          "cum_vwap_num": 107552.75,
          "cum_vol": 15230,
          "iv": 15.65,
          "coi": -308
        },
        "985": {
          "ema_ltp": 8.3421875,
          "cum_vwap_num": 61904.649999999994,
          "cum_vol": 7181,
          "iv": 15.77,
          "coi": -56
        },
        "990": {
          "ema_ltp": 10.084375,
          "cum_vwap_num": 234507.15,
          "cum_vol": 22706,
          "iv": 15.5,
          "coi": -255
        },
        "995": {
          "ema_ltp": 11.9984375,
          "cum_vwap_num": 173636.69999999998,
          "cum_vol": 14165,
          "iv": 15.47,
          "coi": 140
        },
        "1000": {
          "ema_ltp": 14.15625,
          "cum_vwap_num": 689368.85,
          "cum_vol": 47518,
          "iv": 15.45,
          "coi": 460
        },
        "1005": {
          "ema_ltp": 16.5265625,
          "cum_vwap_num": 157164.65,
          "cum_vol": 9300,
          "iv": 15.4,
          "coi": 149
        },
        "1010": {
          "ema_ltp": 19.331249999999997,
          "cum_vwap_num": 178826.99999999997,
          "cum_vol": 9085,
          "iv": 15.6,
          "coi": 225
        },
        "1015": {
          "ema_ltp": 22.3265625,
          "cum_vwap_num": 26603.899999999998,
          "cum_vol": 1166,
          "iv": 15.77,
          "coi": 28
        },
        "1020": {
          "ema_ltp": 25.5328125,
          "cum_vwap_num": 56567.85,
          "cum_vol": 2178,
          "iv": 15.78,
          "coi": 19
        },
        "1025": {
          "ema_ltp": 29.1,
          "cum_vwap_num": 2066.1,
          "cum_vol": 71,
          "iv": 16.24,
          "coi": -10
        }
      },
      "meta": {
        "underlying": 998.4
      }
    },
    "BHARTIARTL": {
      "strikes": {
        "2000": {
          "ema_ltp": 4.690872928960016,
          "cum_vwap_num": 182462.9,
          "cum_vol": 32609,
          "iv": 16.61,
          "coi": -317
        },
        "2020": {
          "ema_ltp": 7.165381347358926,
          "cum_vwap_num": 172970.9,
          "cum_vol": 20566,
          "iv": 16.35,
          "coi": 43
        },
        "2040": {
          "ema_ltp": 10.695214341697284,
          "cum_vwap_num": 369847.19999999995,
          "cum_vol": 29926,
          "iv": 16.28,
          "coi": 379
        },
        "2060": {
          "ema_ltp": 15.430375992527114,
          "cum_vwap_num": 770966.2999999999,
          "cum_vol": 43593,
          "iv": 16.0,
          "coi": 289
        },
        "2080": {
          "ema_ltp": 21.83342754502373,
          "cum_vwap_num": 1207411.05,
          "cum_vol": 49206,
          "iv": 15.96,
          "coi": -4
        },
        "2100": {
          "ema_ltp": 30.119477304886097,
          "cum_vwap_num": 2611272.1500000004,
          "cum_vol": 80645,
          "iv": 15.9,
          "coi": -24
        },
        "2120": {
          "ema_ltp": 40.36313820339565,
          "cum_vwap_num": 923777.8,
          "cum_vol": 22149,
          "iv": 16.06,
          "coi": -41
        },
        "2140": {
          "ema_ltp": 52.469128957009524,
          "cum_vwap_num": 674969.8499999999,
          "cum_vol": 12692,
          "iv": 16.28,
          "coi": -61
        },
        "2160": {
          "ema_ltp": 66.55340854175157,
          "cum_vwap_num": 102889.65000000001,
          "cum_vol": 1518,
          "iv": 16.91,
          "coi": -11
        },
        "2180": {
          "ema_ltp": 81.78494690906808,
          "cum_vwap_num": 262928.3000000001,
          "cum_vol": 3322,
          "iv": 16.74,
          "coi": -32
        },
        "2200": {
          "ema_ltp": 93.5,
          "cum_vwap_num": 6826.45,
          "cum_vol": 73,
          "iv": 17.04,
          "coi": -7
        }
      },
      "meta": {
        "underlying": 2101.0
      }
    },
    "SBIN": {
      "strikes": {
        "925": {
          "ema_ltp": 5.516455078125,
          "cum_vwap_num": 36374.05,
          "cum_vol": 6403,
          "iv": 16.56,
          "coi": 102
        },
        "930": {
          "ema_ltp": 6.67576904296875,
          "cum_vwap_num": 179190.0,
          "cum_vol": 26142,
          "iv": 16.27,
          "coi": 283
        },
        "935": {
          "ema_ltp": 8.11422119140625,
          "cum_vwap_num": 98454.35,
          "cum_vol": 11887,
          "iv": 16.25,
          "coi": 66
        },
        "940": {
          "ema_ltp": 9.66151123046875,
          "cum_vwap_num": 407602.1,
          "cum_vol": 41048,
          "iv": 15.94,
          "coi": 148
        },
        "945": {
          "ema_ltp": 11.5614990234375,
          "cum_vwap_num": 390172.15,
          "cum_vol": 32861,
          "iv": 15.89,
          "coi": 198
        },
        "950": {
          "ema_ltp": 13.77562255859375,
          "cum_vwap_num": 1137923.6500000001,
          "cum_vol": 80974,
          "iv": 16.0,
          "coi": 1162
        },
        "955": {
          "ema_ltp": 16.1474609375,
          "cum_vwap_num": 285136.85000000003,
          "cum_vol": 17507,
          "iv": 16.06,
          "coi": 75
        },
        "960": {
          "ema_ltp": 18.8653076171875,
          "cum_vwap_num": 743528.7000000001,
          "cum_vol": 39024,
          "iv": 16.18,
          "coi": 139
        },
        "965": {
          "ema_ltp": 21.7845703125,
          "cum_vwap_num": 180832.19999999998,
          "cum_vol": 8311,
          "iv": 16.31,
          "coi": -25
        },
        "970": {
          "ema_ltp": 25.056396484375,
          "cum_vwap_num": 235047.4,
          "cum_vol": 9484,
          "iv": 16.22,
          "coi": -43
        },
        "975": {
          "ema_ltp": 28.8,
          "cum_vwap_num": 4578.700000000001,
          "cum_vol": 159,
          "iv": 16.42,
          "coi": -30
        }
      },
      "meta": {
        "underlying": 948.2
      }
    },
    "AXISBANK": {
      "strikes": {
        "1230": {
          "ema_ltp": 5.330805015563964,
          "cum_vwap_num": 36456.5,
          "cum_vol": 5819,
          "iv": 18.02,
          "coi": 23
        },
        "1240": {
          "ema_ltp": 7.006928443908691,
          "cum_vwap_num": 91055.65,
          "cum_vol": 11262,
          "iv": 17.79,
          "coi": 83
        },
        "1250": {
          "ema_ltp": 9.347507095336914,
          "cum_vwap_num": 174331.35,
          "cum_vol": 16207,
          "iv": 17.67,
          "coi": -4
        },
        "1260": {
          "ema_ltp": 12.088884162902833,
          "cum_vwap_num": 340558.95,
          "cum_vol": 24604,
          "iv": 17.7,
          "coi": -45
        },
        "1270": {
          "ema_ltp": 15.539148902893066,
          "cum_vwap_num": 310467.55,
          "cum_vol": 18288,
          "iv": 17.42,
          "coi": 29
        },
        "1280": {
          "ema_ltp": 19.660962295532226,
          "cum_vwap_num": 385274.3,
          "cum_vol": 18397,
          "iv": 17.51,
          "coi": -58
        },
        "1290": {
          "ema_ltp": 24.790864753723145,
          "cum_vwap_num": 105342.74999999999,
          "cum_vol": 4059,
          "iv": 17.4,
          "coi": -20
        },
        "1300": {
          "ema_ltp": 30.414142417907712,
          "cum_vwap_num": 112253.15,
          "cum_vol": 3484,
          "iv": 17.52,
          "coi": -38
        },
        "1310": {
          "ema_ltp": 0.010284996032714844,
          "cum_vwap_num": 730.55,
          "cum_vol": 17,
          "iv": 0.0,
          "coi": 0
        },
        "1320": {
          "ema_ltp": 43.74340400695801,
          "cum_vwap_num": 53036.5,
          "cum_vol": 1184,
          "iv": 18.49,
          "coi": -36
        },
        "1330": {
          "ema_ltp": 0.0,
          "cum_vwap_num": 0.0,
          "cum_vol": 0,
          "iv": 0.0,
          "coi": 0
        }
      },
      "meta": {
        "underlying": 1279.5
      }
    },
    "MARUTI": {
      "strikes": {
        "15500": {
          "ema_ltp": 79.0375,
          "cum_vwap_num": 1591903.45,
          "cum_vol": 19994,
          "iv": 16.79,
          "coi": 236
        },
        "15600": {
          "ema_ltp": 99.84375,
          "cum_vwap_num": 350780.0,
          "cum_vol": 3471,
          "iv": 16.54,
          "coi": -30
        },
        "15700": {
          "ema_ltp": 125.9,
          "cum_vwap_num": 724402.9,
          "cum_vol": 5709,
          "iv": 16.49,
          "coi": 1
        },
        "15800": {
          "ema_ltp": 156.5375,
          "cum_vwap_num": 1214970.8,
          "cum_vol": 7674,
          "iv": 16.47,
          "coi": -155
        },
        "15900": {
          "ema_ltp": 191.49375,
          "cum_vwap_num": 1503607.95,
          "cum_vol": 7794,
          "iv": 16.34,
          "coi": 44
        },
        "16000": {
          "ema_ltp": 233.51875,
          "cum_vwap_num": 4987769.75,
          "cum_vol": 21198,
          "iv": 16.1,
          "coi": 83
        },
        "16100": {
          "ema_ltp": 278.7,
          "cum_vwap_num": 1756786.5999999999,
          "cum_vol": 6225,
          "iv": 16.13,
          "coi": 46
        },
        "16200": {
          "ema_ltp": 333.98749999999995,
          "cum_vwap_num": 1868017.6,
          "cum_vol": 5537,
          "iv": 16.1,
          "coi": -42
        },
        "16300": {
          "ema_ltp": 393.875,
          "cum_vwap_num": 1766113.0999999999,
          "cum_vol": 4440,
          "iv": 15.91,
          "coi": 165
        },
        "16400": {
          "ema_ltp": 463.625,
          "cum_vwap_num": 52177.4,
          "cum_vol": 110,
          "iv": 16.29,
          "coi": 6
        },
        "16500": {
          "ema_ltp": 525.6937499999999,
          "cum_vwap_num": 101942.25,
          "cum_vol": 193,
          "iv": 16.62,
          "coi": -16
        }
      },
      "meta": {
        "underlying": 15989.0
      }
    },
    "HINDUNILVR": {
      "strikes": {
        "2360": {
          "ema_ltp": 0.056696510314941405,
          "cum_vwap_num": 31411.400000000005,
          "cum_vol": 61332,
          "iv": 29.63,
          "coi": -277
        },
        "2380": {
          "ema_ltp": 0.06386591485770624,
          "cum_vwap_num": 165709.05,
          "cum_vol": 170049,
          "iv": 24.08,
          "coi": 773
        },
        "2400": {
          "ema_ltp": 0.07956927478844592,
          "cum_vwap_num": 721415.4999999999,
          "cum_vol": 404605,
          "iv": 18.45,
          "coi": -592
        },
        "2420": {
          "ema_ltp": 0.12196662436454062,
          "cum_vwap_num": 983496.0000000001,
          "cum_vol": 326582,
          "iv": 12.68,
          "coi": -376
        },
        "2440": {
          "ema_ltp": 0.3567842166377887,
          "cum_vwap_num": 2044379.1499999997,
          "cum_vol": 349657,
          "iv": 6.64,
          "coi": -112
        },
        "2460": {
          "ema_ltp": 2.7633131353806677,
          "cum_vwap_num": 3198671.649999999,
          "cum_vol": 251297,
          "iv": 2.84,
          "coi": -787
        },
        "2480": {
          "ema_ltp": 17.678089887280112,
          "cum_vwap_num": 2441588.900000001,
          "cum_vol": 99346,
          "iv": 0.0,
          "coi": -179
        },
        "2500": {
          "ema_ltp": 39.503187995284314,
          "cum_vwap_num": 1824772.7999999998,
          "cum_vol": 46615,
          "iv": 0.0,
          "coi": -188
        },
        "2520": {
          "ema_ltp": 42.03360032704677,
          "cum_vwap_num": 238905.75,
          "cum_vol": 4271,
          "iv": 0.0,
          "coi": -55
        },
        "2540": {
          "ema_ltp": 71.97311293408403,
          "cum_vwap_num": 135452.15000000002,
          "cum_vol": 1754,
          "iv": 0.0,
          "coi": -43
        },
        "2560": {
          "ema_ltp": 97.5140625,
          "cum_vwap_num": 17823.45,
          "cum_vol": 180,
          "iv": 0.0,
          "coi": -1
        }
      },
      "meta": {
        "underlying": 2456.0
      }
    },
    "BAJFINANCE": {
      "strikes": {
        "980": {
          "ema_ltp": 5.65859375,
          "cum_vwap_num": 11461.55,
          "cum_vol": 2000,
          "iv": 22.33,
          "coi": -48
        },
        "990": {
          "ema_ltp": 7.602343749999999,
          "cum_vwap_num": 11913.0,
          "cum_vol": 1533,
          "iv": 22.09,
          "coi": -6
        },
        "1000": {
          "ema_ltp": 10.0109375,
          "cum_vwap_num": 58031.4,
          "cum_vol": 5644,
          "iv": 22.11,
          "coi": -5
        },
        "1010": {
          "ema_ltp": 13.2484375,
          "cum_vwap_num": 65499.35,
          "cum_vol": 4858,
          "iv": 22.21,
          "coi": -78
        },
        "1020": {
          "ema_ltp": 17.1109375,
          "cum_vwap_num": 107371.2,
          "cum_vol": 6171,
          "iv": 22.19,
          "coi": -50
        },
        "1030": {
          "ema_ltp": 21.65234375,
          "cum_vwap_num": 114851.75,
          "cum_vol": 5212,
          "iv": 22.28,
          "coi": 155
        },
        "1040": {
          "ema_ltp": 26.9125,
          "cum_vwap_num": 41945.6,
          "cum_vol": 1535,
          "iv": 22.46,
          "coi": 13
        },
        "1050": {
          "ema_ltp": 32.813281249999996,
          "cum_vwap_num": 16948.05,
          "cum_vol": 511,
          "iv": 22.57,
          "coi": -20
        },
        "1060": {
          "ema_ltp": 39.234375,
          "cum_vwap_num": 4086.1499999999996,
          "cum_vol": 101,
          "iv": 22.92,
          "coi": -2
        },
        "1070": {
          "ema_ltp": 0.0,
          "cum_vwap_num": 0.0,
          "cum_vol": 0,
          "iv": 0.0,
          "coi": 0
        },
        "1080": {
          "ema_ltp": 54.587500000000006,
          "cum_vwap_num": 8702.1,
          "cum_vol": 157,
          "iv": 24.53,
          "coi": -2
        }
      },
      "meta": {
        "underlying": 1028.9
      }
    },
    "SUNPHARMA": {
      "strikes": {
        "1720": {
          "ema_ltp": 2.9824308033451103,
          "cum_vwap_num": 22057.450000000004,
          "cum_vol": 4320,
          "iv": 16.66,
          "coi": -5
        },
        "1740": {
          "ema_ltp": 4.587880353107731,
          "cum_vwap_num": 169655.6,
          "cum_vol": 26786,
          "iv": 16.03,
          "coi": 31
        },
        "1760": {
          "ema_ltp": 7.16471429508757,
          "cum_vwap_num": 208675.85000000003,
          "cum_vol": 21883,
          "iv": 15.6,
          "coi": 36
        },
        "1780": {
          "ema_ltp": 11.214590955772644,
          "cum_vwap_num": 639838.3,
          "cum_vol": 43977,
          "iv": 15.32,
          "coi": 20
        },
        "1800": {
          "ema_ltp": 16.975133925478914,
          "cum_vwap_num": 2330424.8499999996,
          "cum_vol": 114534,
          "iv": 15.24,
          "coi": 49
        },
        "1820": {
          "ema_ltp": 24.795984295126228,
          "cum_vwap_num": 1394146.999999999,
          "cum_vol": 53163,
          "iv": 15.3,
          "coi": 26
        },
        "1840": {
          "ema_ltp": 36.00820763364855,
          "cum_vwap_num": 1890218.85,
          "cum_vol": 53989,
          "iv": 15.72,
          "coi": -7
        },
        "1860": {
          "ema_ltp": 26.02500377566702,
          "cum_vwap_num": 381478.3999999999,
          "cum_vol": 8527,
          "iv": 0.0,
          "coi": 0
        },
        "1880": {
          "ema_ltp": 0.02091363004103144,
          "cum_vwap_num": 189878.85000000018,
          "cum_vol": 3149,
          "iv": 0.0,
          "coi": 0
        },
        "1900": {
          "ema_ltp": 74.89794311523437,
          "cum_vwap_num": 2983.6000000000004,
          "cum_vol": 37,
          "iv": 15.88,
          "coi": 2
        },
        "1920": {
          "ema_ltp": 0.0,
          "cum_vwap_num": 0.0,
          "cum_vol": 0,
          "iv": 0.0,
          "coi": 0
        }
      },
      "meta": {
        "underlying": 1817.4
      }
    },
    "NIFTY": {
      "meta": {
        "underlying": 26027.85
      }
    },
    "BANKNIFTY": {
      "meta": {
        "underlying": 59294.6
      }
    },
    "TCS": {
      "meta": {
        "underlying": 3228.9
      }
    },
    "ICICIBANK": {
      "meta": {
        "underlying": 1386.1
      }
    },
    "KOTAKBANK": {
      "meta": {
        "underlying": 2134.3
      }
    },
    "ITC": {
      "meta": {
        "underlying": 403.25
      }
    },
    "LT": {
      "meta": {
        "underlying": 3976.8
      }
    },
    "ADANIENT": {
      "meta": {
        "underlying": 2218.2
      }
    },
    "ULTRACEMCO": {
      "meta": {
        "underlying": 11611.0
      }
    },
    "WIPRO": {
      "meta": {
        "underlying": 257.01
      }
    }
  }
}